roboversion/__init__.py
roboversion/__main__.py
roboversion/git.py
roboversion/version.py
roboversion-2.0.0.dist-info/LICENSE
roboversion-2.0.0.dist-info/METADATA
roboversion-2.0.0.dist-info/WHEEL
roboversion-2.0.0.dist-info/entry_points.txt
roboversion-2.0.0.dist-info/top_level.txt
roboversion-2.0.0.dist-info/RECORD
