Metadata-Version: 2.1
Name: roboversion
Version: 2.0.0
Summary: Automated project versioning using Git repository state
Home-page: https://github.com/dsfinn/roboversion.git
Author: David Finn
Author-email: dsfinn@gmail.com
License: UNKNOWN
Platform: UNKNOWN
Classifier: Programming Language :: Python :: 3.6
Classifier: License :: OSI Approved :: GNU General Public License v3 or later (GPLv3+)
Classifier: Operating System :: OS Independent
Classifier: Intended Audience :: Developers
Classifier: Topic :: Software Development :: Version Control
Classifier: Topic :: Software Development :: Version Control :: Git
Classifier: Topic :: Utilities
Requires-Python: >=3.6
